chaikin_smoothing/__init__.py
chaikin_smoothing/chaikin_smoothing.py
smooth/__init__.py
smooth/chaikin_smoothing.py
chaikin_smoothing-0.0.1.dist-info/LICENSE
chaikin_smoothing-0.0.1.dist-info/METADATA
chaikin_smoothing-0.0.1.dist-info/WHEEL
chaikin_smoothing-0.0.1.dist-info/top_level.txt
chaikin_smoothing-0.0.1.dist-info/RECORD
